subtle_wired/__init__.py
subtle_wired/core/__init__.py
subtle_wired/core/base/__init__.py
subtle_wired/core/base/singleton.py
subtle_wired/core/component.py
subtle_wired/core/container.py
subtle_wired/core/injector.py
subtle_wired/decorators/__init__.py
subtle_wired/decorators/component.py
subtle_wired/decorators/injection.py
subtle_wired-1.0.1.dist-info/LICENSE
subtle_wired-1.0.1.dist-info/METADATA
subtle_wired-1.0.1.dist-info/WHEEL
subtle_wired-1.0.1.dist-info/RECORD
