Metadata-Version: 2.3
Name: subtle-wired
Version: 1.0.1
Summary: A simple reflection-based dependency injector.
License: MIT License
Keywords: subtle-wired,dependency-injection,dependency,injector,DI,uncouple,reflection,python
Author: Willian Antonio dos Santos
Requires-Python: >=3.10,<4.0
Classifier: Programming Language :: Python :: 3
Classifier: Programming Language :: Python :: 3.10
Classifier: Programming Language :: Python :: 3.11
Classifier: Programming Language :: Python :: 3.12
Classifier: License :: OSI Approved :: MIT License
Classifier: Operating System :: OS Independent
Project-URL: Documentation, https://github.com/Will1Dexter/subtle-wired/blob/master/README.md
Project-URL: Homepage, https://github.com/Will1Dexter/subtle-wired
Project-URL: Issues, https://github.com/Will1Dexter/subtle-wired/issues
Project-URL: Repository, https://github.com/Will1Dexter/subtle-wired
